{"side":1,"date":"1941-12-07T00:00:00","hexes":[{"x":82,"y":74,"units":[{"row":null,"name":null,"id":0,"x":82,"y":74,"type":7,"location":null,"owner":0,"report":"Morning Air attack on Tuguegarao , at 82,74 \r\n \r\nWeather in hex: Clear sky\r\n \r\nRaid spotted at 16 NM, estimated altitude 19,000 feet.\r\nEstimated time to target is 4 minutes\r\n \r\nJapanese aircraft\r\n      Ki-48-Ib Lily x 27\r\n \r\nNo Japanese losses\r\n \r\nAirbase hits 5\r\nAirbase supply hits 1\r\nRunway hits 8\r\n \r\nAircraft Attacking:\r\n      27 x Ki-48-Ib Lily bombing from 15000 feet\r\n               Airfield Attack:  4 x 100 kg GP Bomb\r\n \r\n \r\n \r\n","subunits":[],"type_str":"AfterAction"}]},{"x":89,"y":95,"units":[{"row":null,"name":null,"id":0,"x":89,"y":95,"type":8,"location":null,"owner":0,"report":"F1M2 Pete sighting report: 3 Allied ships at 89,95 near Babeldaob, speed 17, Moving Southeast","subunits":[],"type_str":"OperationalReport"}]}]}